{
  "_class": "symbolInstance",
  "booleanOperation": 0,
  "do_objectID": "22BEC9B8-6188-407E-99F1-D6A05E81FDCD",
  "exportOptions": {
    "_class": "exportOptions",
    "do_objectID": "64364CE8-0DBB-43DE-BB49-49D11DA32B30",
    "exportFormats": [
    ],
    "includedLayerIds": [
    ],
    "layerOptions": 0,
    "shouldTrim": false
  },
  "frame": {
    "_class": "rect",
    "constrainProportions": false,
    "do_objectID": "7714745F-E024-42D1-85DA-79AC3D061CD8",
    "height": 50,
    "width": 50,
    "x": 0,
    "y": 0
  },
  "horizontalSpacing": 0,
  "isFixedToViewport": false,
  "isFlippedHorizontal": false,
  "isFlippedVertical": false,
  "isLocked": true,
  "isVisible": true,
  "layerListExpandedType": 0,
  "name": "Colors / Red / Red 500 Copy 30",
  "nameIsFixed": false,
  "overrideValues": [
  ],
  "resizingConstraint": 63,
  "resizingType": 0,
  "rotation": 0,
  "scale": 1,
  "shouldBreakMaskChain": false,
  "style": {
    "_class": "style",
    "do_objectID": "0517F106-CB91-482D-B9BD-13B848868201",
    "endMarkerType": 0,
    "miterLimit": 10,
    "startMarkerType": 0,
    "windingRule": 1
  },
  "symbolID": "6964B3C9-144F-42EF-9145-6CCC846029D4",
  "verticalSpacing": 0
}