{
  "_class": "symbolInstance",
  "do_objectID": "806BF0D1-2441-4748-8035-6EF17BD8E544",
  "exportOptions": {
    "_class": "exportOptions",
    "do_objectID": "42A18411-0A11-41A8-980F-0F66702E70EF",
    "exportFormats": [
    ],
    "includedLayerIds": [
    ],
    "layerOptions": 0,
    "shouldTrim": false
  },
  "frame": {
    "_class": "rect",
    "constrainProportions": false,
    "do_objectID": "8DE495A1-949E-4A87-B595-46B61077C149",
    "height": 85,
    "width": 230,
    "x": 0,
    "y": 0
  },
  "horizontalSpacing": 0,
  "isFlippedHorizontal": false,
  "isFlippedVertical": false,
  "isLocked": false,
  "isVisible": true,
  "layerListExpandedType": 0,
  "name": "Location",
  "nameIsFixed": true,
  "overrideValues": [
  ],
  "overrides": {
  },
  "resizingConstraint": 18,
  "resizingType": 0,
  "rotation": 0,
  "scale": 1,
  "shouldBreakMaskChain": false,
  "style": {
    "_class": "style",
    "do_objectID": "C6DCAC3D-5947-4097-A8DA-015B9C9CE5B1",
    "endDecorationType": 0,
    "miterLimit": 10,
    "startDecorationType": 0
  },
  "symbolID": "FA8B90E3-ACF5-4752-98FA-6080FFF6E753",
  "userInfo": {
    "com.animaapp.stc-sketch-plugin": {
      "kModelPropertiesKey": {
      }
    }
  },
  "verticalSpacing": 0
}