{
  "_class": "symbolInstance",
  "booleanOperation": 0,
  "clippingMaskMode": 0,
  "do_objectID": "07368121-8609-4C15-82EF-CCB3142F0E9B",
  "exportOptions": {
    "_class": "exportOptions",
    "do_objectID": "E3AD8DA7-A69F-4C4F-8AA4-9AC7BFF42224",
    "exportFormats": [
    ],
    "includedLayerIds": [
    ],
    "layerOptions": 0,
    "shouldTrim": false
  },
  "frame": {
    "_class": "rect",
    "constrainProportions": false,
    "do_objectID": "626383A2-59DE-4371-AEB2-96F95A86DD41",
    "height": 36,
    "width": 241,
    "x": 0,
    "y": 0
  },
  "hasClippingMask": false,
  "horizontalSpacing": 0,
  "isFixedToViewport": false,
  "isFlippedHorizontal": false,
  "isFlippedVertical": false,
  "isLocked": false,
  "isVisible": true,
  "layerListExpandedType": 0,
  "name": "State",
  "nameIsFixed": true,
  "overrideValues": [
  ],
  "resizingConstraint": 10,
  "resizingType": 0,
  "rotation": 0,
  "scale": 1,
  "shouldBreakMaskChain": false,
  "style": {
    "_class": "style",
    "do_objectID": "3BDC4BC5-200B-43B7-BBF5-8A608B259472",
    "endMarkerType": 0,
    "miterLimit": 10,
    "startMarkerType": 0,
    "windingRule": 1
  },
  "symbolID": "20F0993D-1CFA-4CB1-ACBD-4A046679FD20",
  "verticalSpacing": 0
}