{
  "_class": "shapeGroup",
  "clippingMaskMode": 0,
  "do_objectID": "F387F66D-7DF0-4473-8B5D-1F477503C872",
  "exportOptions": {
    "_class": "exportOptions",
    "exportFormats": [
    ],
    "includedLayerIds": [
    ],
    "layerOptions": 0,
    "shouldTrim": false
  },
  "frame": {
    "_class": "rect",
    "constrainProportions": false,
    "height": 13.89637709388391,
    "width": 100.2589490919873,
    "x": 39.73665757693807,
    "y": 12.74561745227892
  },
  "hasClickThrough": false,
  "hasClippingMask": false,
  "isFlippedHorizontal": false,
  "isFlippedVertical": false,
  "isLocked": false,
  "isVisible": true,
  "layerListExpandedType": 1,
  "layers": [
    {
      "class": "shapePath",
      "id": "7FB1E98D-1644-4ADD-BCD1-A053E0384EFB"
    },
    {
      "class": "shapePath",
      "id": "A5963C44-56FD-4221-A4D7-43ACEF9EC1EF"
    },
    {
      "class": "shapePath",
      "id": "2DB8FED6-A407-48F0-9018-1C71A010C2EF"
    },
    {
      "class": "shapePath",
      "id": "6F99FA0B-F401-42A5-BDC7-063774FE42C8"
    },
    {
      "class": "shapePath",
      "id": "2EF71292-64F8-4ACD-AC93-94BE7F3BED60"
    },
    {
      "class": "shapePath",
      "id": "5D848085-CC54-4E78-A7F9-D51B2DB62588"
    },
    {
      "class": "shapePath",
      "id": "9C79FDCA-BDBF-4117-B4C5-4ABDF17C65A4"
    },
    {
      "class": "shapePath",
      "id": "770A2F10-F8E3-4DED-A227-485C3461D613"
    }
  ],
  "name": "Shape",
  "nameIsFixed": false,
  "resizingConstraint": 63,
  "resizingType": 0,
  "rotation": 0,
  "shouldBreakMaskChain": false,
  "style": {
    "_class": "style",
    "endDecorationType": 0,
    "fills": [
      {
        "_class": "fill",
        "color": {
          "_class": "color",
          "alpha": 1,
          "blue": 1,
          "green": 1,
          "red": 1
        },
        "fillType": 0,
        "isEnabled": true,
        "noiseIndex": 0,
        "noiseIntensity": 0,
        "patternFillType": 1,
        "patternTileScale": 1
      }
    ],
    "miterLimit": 10,
    "startDecorationType": 0
  },
  "windingRule": 0
}