{
  "_class": "shapeGroup",
  "clippingMaskMode": 0,
  "do_objectID": "D2C42ECB-E338-47EC-80AB-FF278B819B77",
  "exportOptions": {
    "_class": "exportOptions",
    "exportFormats": [
      {
        "_class": "exportFormat",
        "absoluteSize": 0,
        "fileFormat": "svg",
        "name": "",
        "namingScheme": 0,
        "scale": 1,
        "visibleScaleType": 0
      }
    ],
    "includedLayerIds": [
    ],
    "layerOptions": 0,
    "shouldTrim": false
  },
  "frame": {
    "_class": "rect",
    "constrainProportions": true,
    "height": 7.681677462648244,
    "width": 12,
    "x": 12,
    "y": 28
  },
  "hasClickThrough": false,
  "hasClippingMask": false,
  "isFlippedHorizontal": false,
  "isFlippedVertical": false,
  "isLocked": true,
  "isVisible": true,
  "layerListExpandedType": 0,
  "layers": [
    {
      "class": "shapePath",
      "id": "C16840B6-FFED-4259-B6F8-D993AEDF93CE"
    }
  ],
  "name": "Path 2 Copy 6",
  "nameIsFixed": false,
  "resizingConstraint": 63,
  "resizingType": 0,
  "rotation": -90,
  "shouldBreakMaskChain": false,
  "style": {
    "_class": "style",
    "endDecorationType": 0,
    "fills": [
      {
        "_class": "fill",
        "color": {
          "_class": "color",
          "alpha": 1,
          "blue": 1,
          "green": 1,
          "red": 1
        },
        "fillType": 0,
        "isEnabled": true,
        "noiseIndex": 0,
        "noiseIntensity": 0,
        "patternFillType": 1,
        "patternTileScale": 1
      }
    ],
    "miterLimit": 10,
    "sharedObjectID": "2A8A91D6-716D-4617-90F9-AA62FC2A64C2",
    "startDecorationType": 0
  },
  "userInfo": {
    "com.animaapp.stc-sketch-plugin": {
      "kModelPropertiesKey": {
        "constraints": {
          "aspectRatio": {
            "constant": 7.681677,
            "enabled": 1,
            "modelID": "constraint_82f1a1b2-6eca-49ab-8e5b-4aa781a9da65",
            "model_class": "ADModelConstraint",
            "model_version": 0.1,
            "multiplier": 12
          },
          "automatic": 1,
          "modelID": "viewConstraints_e411b98e-81f6-4e86-a9b2-d4f68c1eb6a9",
          "model_class": "ADModelViewConstraints",
          "model_version": 0.1,
          "scaleFactor": 1
        }
      }
    }
  },
  "windingRule": 0
}