{
  "_class": "shapePath",
  "booleanOperation": 1,
  "do_objectID": "2CC36136-ADF0-4A8A-B2E1-EB59846590A9",
  "edited": true,
  "exportOptions": {
    "_class": "exportOptions",
    "exportFormats": [
    ],
    "includedLayerIds": [
    ],
    "layerOptions": 0,
    "shouldTrim": false
  },
  "frame": {
    "_class": "rect",
    "constrainProportions": false,
    "height": 6.002146484375,
    "width": 4.034999999999999,
    "x": 5.0002,
    "y": 5.516703515625
  },
  "isClosed": true,
  "isFlippedHorizontal": false,
  "isFlippedVertical": false,
  "isLocked": false,
  "isVisible": true,
  "layerListExpandedType": 0,
  "name": "Combined-Shape-path",
  "nameIsFixed": false,
  "pointRadiusBehaviour": 1,
  "points": [
    {
      "_class": "curvePoint",
      "cornerRadius": 0,
      "curveFrom": "{0.87608426270136308, 0.83339293657640057}",
      "curveMode": 4,
      "curveTo": "{0.9444857496902106, 0.83339293657640057}",
      "hasCurveFrom": false,
      "hasCurveTo": true,
      "point": "{0.87608426270136308, 0.83339293657640057}"
    },
    {
      "_class": "curvePoint",
      "cornerRadius": 0,
      "curveFrom": "{0.74275092936802967, 0.61213875634986048}",
      "curveMode": 4,
      "curveTo": "{0.74175960346964065, 0.83339293657640057}",
      "hasCurveFrom": true,
      "hasCurveTo": false,
      "point": "{0.74175960346964065, 0.83339293657640057}"
    },
    {
      "_class": "curvePoint",
      "cornerRadius": 0,
      "curveFrom": "{0.74027261462205696, 0.019684038815540924}",
      "curveMode": 3,
      "curveTo": "{0.7425030978934325, 0.1426400516221574}",
      "hasCurveFrom": true,
      "hasCurveTo": true,
      "point": "{0.7410161090458488, 0.061502411734864447}"
    },
    {
      "_class": "curvePoint",
      "cornerRadius": 0,
      "curveFrom": "{0.61486988847583635, 0.00085744064867425971}",
      "curveMode": 2,
      "curveTo": "{0.71251548946716226, -0.00080862998556184746}",
      "hasCurveFrom": true,
      "hasCurveTo": true,
      "point": "{0.6617100371747211, 2.4405331556132139e-05}"
    },
    {
      "_class": "curvePoint",
      "cornerRadius": 0,
      "curveFrom": "{0.5216852540272614, 0.00019101239497978725}",
      "curveMode": 4,
      "curveTo": "{0.56852540272614627, 0.00035761945840344237}",
      "hasCurveFrom": false,
      "hasCurveTo": true,
      "point": "{0.5216852540272614, 0.00019101239497978725}"
    },
    {
      "_class": "curvePoint",
      "cornerRadius": 0,
      "curveFrom": "{0.40148698884758355, 0.00035761945840344237}",
      "curveMode": 4,
      "curveTo": "{0.4411400247831474, 0.00019101239497978725}",
      "hasCurveFrom": true,
      "hasCurveTo": false,
      "point": "{0.4411400247831474, 0.00019101239497978725}"
    },
    {
      "_class": "curvePoint",
      "cornerRadius": 0,
      "curveFrom": "{0.32242874845105318, 0.00019101239497978725}",
      "curveMode": 3,
      "curveTo": "{0.36208178438661703, 0.00035761945840344237}",
      "hasCurveFrom": true,
      "hasCurveTo": true,
      "point": "{0.32267657992565052, 0.00019101239497978725}"
    },
    {
      "_class": "curvePoint",
      "cornerRadius": 0,
      "curveFrom": "{0.32218091697645601, 0.00019101239497978725}",
      "curveMode": 4,
      "curveTo": "{0.32242874845105318, 0.00019101239497978725}",
      "hasCurveFrom": false,
      "hasCurveTo": true,
      "point": "{0.32218091697645601, 0.00019101239497978725}"
    },
    {
      "_class": "curvePoint",
      "cornerRadius": 0,
      "curveFrom": "{0.055266418835192045, 0.00019101239497978725}",
      "curveMode": 4,
      "curveTo": "{0.12391573729863695, 0.00019101239497978725}",
      "hasCurveFrom": true,
      "hasCurveTo": false,
      "point": "{0.12391573729863695, 0.00019101239497978725}"
    },
    {
      "_class": "curvePoint",
      "cornerRadius": 0,
      "curveFrom": "{0, 0.12947809361169293}",
      "curveMode": 2,
      "curveTo": "{0, 0.037510994601866104}",
      "hasCurveFrom": true,
      "hasCurveTo": true,
      "point": "{0, 0.08349454410677952}"
    },
    {
      "_class": "curvePoint",
      "cornerRadius": 0,
      "curveFrom": "{0.12391573729863695, 0.16679807581857925}",
      "curveMode": 4,
      "curveTo": "{0.055266418835192045, 0.16679807581857925}",
      "hasCurveFrom": false,
      "hasCurveTo": true,
      "point": "{0.12391573729863695, 0.16679807581857925}"
    },
    {
      "_class": "curvePoint",
      "cornerRadius": 0,
      "curveFrom": "{0.2463444857496902, 0.34056924296939339}",
      "curveMode": 4,
      "curveTo": "{0.24708798017348205, 0.16679807581857925}",
      "hasCurveFrom": true,
      "hasCurveTo": false,
      "point": "{0.24708798017348205, 0.16679807581857925}"
    },
    {
      "_class": "curvePoint",
      "cornerRadius": 0,
      "curveFrom": "{0.24708798017348205, 0.83339293657640057}",
      "curveMode": 4,
      "curveTo": "{0.2463444857496902, 0.66212087537694053}",
      "hasCurveFrom": false,
      "hasCurveTo": true,
      "point": "{0.24708798017348205, 0.83339293657640057}"
    },
    {
      "_class": "curvePoint",
      "cornerRadius": 0,
      "curveFrom": "{0.055266418835192045, 0.83339293657640057}",
      "curveMode": 4,
      "curveTo": "{0.12391573729863695, 0.83339293657640057}",
      "hasCurveFrom": true,
      "hasCurveTo": false,
      "point": "{0.12391573729863695, 0.83339293657640057}"
    },
    {
      "_class": "curvePoint",
      "cornerRadius": 0,
      "curveFrom": "{0, 0.96268001779311363}",
      "curveMode": 2,
      "curveTo": "{0, 0.87071291878328683}",
      "hasCurveFrom": true,
      "hasCurveTo": true,
      "point": "{0, 0.91669646828820028}"
    },
    {
      "_class": "curvePoint",
      "cornerRadius": 0,
      "curveFrom": "{0.12391573729863695, 1}",
      "curveMode": 4,
      "curveTo": "{0.055266418835192045, 1}",
      "hasCurveFrom": false,
      "hasCurveTo": true,
      "point": "{0.12391573729863695, 1}"
    },
    {
      "_class": "curvePoint",
      "cornerRadius": 0,
      "curveFrom": "{0.9444857496902106, 1}",
      "curveMode": 4,
      "curveTo": "{0.87608426270136308, 1}",
      "hasCurveFrom": true,
      "hasCurveTo": false,
      "point": "{0.87608426270136308, 1}"
    },
    {
      "_class": "curvePoint",
      "cornerRadius": 0,
      "curveFrom": "{1, 0.87071291878328683}",
      "curveMode": 2,
      "curveTo": "{1, 0.96268001779311363}",
      "hasCurveFrom": true,
      "hasCurveTo": true,
      "point": "{1, 0.91669646828820028}"
    }
  ],
  "resizingConstraint": 63,
  "resizingType": 0,
  "rotation": 0,
  "shouldBreakMaskChain": false
}