{
  "_class": "symbolInstance",
  "booleanOperation": 0,
  "clippingMaskMode": 0,
  "do_objectID": "D6814C9F-7F95-45D9-A7DF-6915D2A10342",
  "exportOptions": {
    "_class": "exportOptions",
    "exportFormats": [
    ],
    "includedLayerIds": [
    ],
    "layerOptions": 0,
    "shouldTrim": false
  },
  "frame": {
    "_class": "rect",
    "constrainProportions": false,
    "height": 16,
    "width": 127,
    "x": 185,
    "y": 146
  },
  "hasClippingMask": false,
  "horizontalSpacing": 0,
  "isFixedToViewport": false,
  "isFlippedHorizontal": false,
  "isFlippedVertical": false,
  "isLocked": false,
  "isVisible": true,
  "layerListExpandedType": 0,
  "name": "Status-Label",
  "nameIsFixed": true,
  "overrideValues": [
    {
      "_class": "overrideValue",
      "do_objectID": "2376C6AB-90BD-4793-9A53-93672EE38DBE",
      "overrideName": "EF471DE5-3048-42DF-99AB-FDD7964F3F44_symbolID",
      "value": ""
    },
    {
      "_class": "overrideValue",
      "do_objectID": "BDF6F146-2FBA-403A-A30E-6220D9CA85AC",
      "overrideName": "6E968B59-C499-414B-8952-6709F309BD56_symbolID",
      "value": "CF887C7A-3346-4D57-8AD1-4C7AA048B6F6"
    }
  ],
  "resizingConstraint": 63,
  "resizingType": 0,
  "rotation": 0,
  "scale": 1,
  "shouldBreakMaskChain": false,
  "style": {
    "_class": "style",
    "endMarkerType": 0,
    "miterLimit": 10,
    "startMarkerType": 0,
    "windingRule": 1
  },
  "symbolID": "668B44E2-F834-4C9F-AE47-E810D7758687",
  "userInfo": {
    "com.animaapp.stc-sketch-plugin": {
      "kModelPropertiesKey": {
      }
    }
  },
  "verticalSpacing": 0
}